bootstrap.py
buildout.cfg
setup.cfg
setup.py
docs/Makefile
docs/make.bat
docs/source/HISTORY.rst
docs/source/README.rst
docs/source/conf.py
docs/source/index.rst
src/zopyx/__init__.py
src/zopyx.convert2.egg-info/PKG-INFO
src/zopyx.convert2.egg-info/SOURCES.txt
src/zopyx.convert2.egg-info/dependency_links.txt
src/zopyx.convert2.egg-info/entry_points.txt
src/zopyx.convert2.egg-info/namespace_packages.txt
src/zopyx.convert2.egg-info/not-zip-safe
src/zopyx.convert2.egg-info/requires.txt
src/zopyx.convert2.egg-info/top_level.txt
src/zopyx/convert2/LICENSE.txt
src/zopyx/convert2/__init__.py
src/zopyx/convert2/calibre.py
src/zopyx/convert2/cli.py
src/zopyx/convert2/config.py
src/zopyx/convert2/convert.py
src/zopyx/convert2/exceptions.py
src/zopyx/convert2/fo.py
src/zopyx/convert2/fop.py
src/zopyx/convert2/header.txt
src/zopyx/convert2/logger.py
src/zopyx/convert2/pdfreactor.py
src/zopyx/convert2/pisa.py
src/zopyx/convert2/pisa_bin.py
src/zopyx/convert2/prince.py
src/zopyx/convert2/registry.py
src/zopyx/convert2/tidy.py
src/zopyx/convert2/util.py
src/zopyx/convert2/version.txt
src/zopyx/convert2/xfc.py
src/zopyx/convert2/xinc.py
src/zopyx/convert2/lib/csstoxslfo/css2xslfo.jar
src/zopyx/convert2/tests/__init__.py
src/zopyx/convert2/tests/data/__init__.py
src/zopyx/convert2/tests/data/test1.html
src/zopyx/convert2/tests/data/test2.html
src/zopyx/convert2/tests/data/test3.html