Metadata-Version: 1.1
Name: zopyx.convert2
Version: 2.4.6
Summary: A Python interface for the conversion of HTML to PDF, RTF, DOCX, WML and ODT) - belongs to zopyx.smartprintng.core
Home-page: http://pypi.python.org/pypi/zopyx.convert2
Author: Andreas Jung
Author-email: info@zopyx.com
License: ZPL (see LICENSE.txt)
Platform: UNKNOWN
Classifier: Programming Language :: Python
